{
    "description": "",
    "tags": [],
    "size": {
        "height": 400,
        "width": 600
    },
    "objects": [
        {
            "id": 448828099,
            "classId": 1485631,
            "description": "",
            "geometryType": "polygon",
            "labelerLogin": "tug85997@temple.edu",
            "createdAt": "2020-05-21T15:17:35.872Z",
            "updatedAt": "2020-05-28T13:38:23.312Z",
            "tags": [],
            "classTitle": "Corrosion",
            "points": {
                "exterior": [
                    [
                        242,
                        79
                    ],
                    [
                        223,
                        81
                    ],
                    [
                        206,
                        85
                    ],
                    [
                        189,
                        90
                    ],
                    [
                        176,
                        94
                    ],
                    [
                        159,
                        103
                    ],
                    [
                        137,
                        114
                    ],
                    [
                        129,
                        117
                    ],
                    [
                        114,
                        125
                    ],
                    [
                        103,
                        131
                    ],
                    [
                        71,
                        142
                    ],
                    [
                        59,
                        147
                    ],
                    [
                        44,
                        154
                    ],
                    [
                        39,
                        152
                    ],
                    [
                        32,
                        149
                    ],
                    [
                        34,
                        154
                    ],
                    [
                        37,
                        156
                    ],
                    [
                        38,
                        159
                    ],
                    [
                        47,
                        163
                    ],
                    [
                        50,
                        162
                    ],
                    [
                        53,
                        158
                    ],
                    [
                        65,
                        154
                    ],
                    [
                        72,
                        155
                    ],
                    [
                        82,
                        159
                    ],
                    [
                        89,
                        161
                    ],
                    [
                        81,
                        164
                    ],
                    [
                        73,
                        167
                    ],
                    [
                        70,
                        170
                    ],
                    [
                        66,
                        173
                    ],
                    [
                        67,
                        176
                    ],
                    [
                        73,
                        179
                    ],
                    [
                        85,
                        171
                    ],
                    [
                        100,
                        168
                    ],
                    [
                        112,
                        162
                    ],
                    [
                        130,
                        158
                    ],
                    [
                        138,
                        154
                    ],
                    [
                        159,
                        145
                    ],
                    [
                        170,
                        142
                    ],
                    [
                        181,
                        140
                    ],
                    [
                        196,
                        135
                    ],
                    [
                        208,
                        131
                    ],
                    [
                        226,
                        125
                    ],
                    [
                        245,
                        119
                    ],
                    [
                        255,
                        114
                    ],
                    [
                        265,
                        113
                    ],
                    [
                        277,
                        110
                    ],
                    [
                        291,
                        103
                    ],
                    [
                        300,
                        99
                    ],
                    [
                        317,
                        94
                    ],
                    [
                        337,
                        88
                    ],
                    [
                        349,
                        84
                    ],
                    [
                        358,
                        78
                    ],
                    [
                        373,
                        73
                    ],
                    [
                        379,
                        73
                    ],
                    [
                        383,
                        69
                    ],
                    [
                        392,
                        63
                    ],
                    [
                        402,
                        55
                    ],
                    [
                        410,
                        47
                    ],
                    [
                        405,
                        48
                    ],
                    [
                        390,
                        56
                    ],
                    [
                        375,
                        61
                    ],
                    [
                        359,
                        67
                    ],
                    [
                        347,
                        70
                    ],
                    [
                        333,
                        73
                    ],
                    [
                        325,
                        78
                    ],
                    [
                        312,
                        82
                    ],
                    [
                        297,
                        87
                    ],
                    [
                        290,
                        87
                    ],
                    [
                        283,
                        84
                    ],
                    [
                        278,
                        85
                    ],
                    [
                        278,
                        92
                    ],
                    [
                        271,
                        98
                    ],
                    [
                        249,
                        104
                    ],
                    [
                        232,
                        110
                    ],
                    [
                        224,
                        115
                    ],
                    [
                        214,
                        117
                    ],
                    [
                        198,
                        123
                    ],
                    [
                        191,
                        127
                    ],
                    [
                        183,
                        131
                    ],
                    [
                        173,
                        135
                    ],
                    [
                        163,
                        139
                    ],
                    [
                        154,
                        142
                    ],
                    [
                        135,
                        149
                    ],
                    [
                        126,
                        150
                    ],
                    [
                        118,
                        150
                    ],
                    [
                        121,
                        146
                    ],
                    [
                        118,
                        142
                    ],
                    [
                        115,
                        138
                    ],
                    [
                        127,
                        134
                    ],
                    [
                        139,
                        132
                    ],
                    [
                        160,
                        127
                    ],
                    [
                        173,
                        120
                    ],
                    [
                        185,
                        118
                    ],
                    [
                        196,
                        113
                    ],
                    [
                        208,
                        111
                    ],
                    [
                        230,
                        105
                    ],
                    [
                        240,
                        97
                    ],
                    [
                        245,
                        92
                    ],
                    [
                        252,
                        86
                    ],
                    [
                        263,
                        82
                    ],
                    [
                        271,
                        79
                    ],
                    [
                        276,
                        78
                    ],
                    [
                        286,
                        72
                    ],
                    [
                        306,
                        66
                    ],
                    [
                        307,
                        62
                    ],
                    [
                        298,
                        62
                    ],
                    [
                        285,
                        67
                    ],
                    [
                        275,
                        71
                    ],
                    [
                        262,
                        76
                    ],
                    [
                        250,
                        79
                    ]
                ],
                "interior": []
            }
        },
        {
            "id": 448828126,
            "classId": 1485631,
            "description": "",
            "geometryType": "polygon",
            "labelerLogin": "tug85997@temple.edu",
            "createdAt": "2020-05-21T15:19:13.877Z",
            "updatedAt": "2020-05-28T13:38:23.312Z",
            "tags": [],
            "classTitle": "Corrosion",
            "points": {
                "exterior": [
                    [
                        453,
                        0
                    ],
                    [
                        449,
                        3
                    ],
                    [
                        435,
                        9
                    ],
                    [
                        424,
                        14
                    ],
                    [
                        411,
                        22
                    ],
                    [
                        404,
                        25
                    ],
                    [
                        400,
                        29
                    ],
                    [
                        405,
                        31
                    ],
                    [
                        411,
                        33
                    ],
                    [
                        423,
                        32
                    ],
                    [
                        424,
                        37
                    ],
                    [
                        419,
                        40
                    ],
                    [
                        434,
                        34
                    ],
                    [
                        443,
                        29
                    ],
                    [
                        448,
                        24
                    ],
                    [
                        458,
                        19
                    ],
                    [
                        449,
                        21
                    ],
                    [
                        442,
                        23
                    ],
                    [
                        430,
                        28
                    ],
                    [
                        430,
                        25
                    ],
                    [
                        436,
                        21
                    ],
                    [
                        445,
                        18
                    ],
                    [
                        458,
                        13
                    ],
                    [
                        466,
                        7
                    ],
                    [
                        475,
                        3
                    ],
                    [
                        483,
                        0
                    ]
                ],
                "interior": []
            }
        },
        {
            "id": 448828138,
            "classId": 1485631,
            "description": "",
            "geometryType": "polygon",
            "labelerLogin": "tug85997@temple.edu",
            "createdAt": "2020-05-21T15:19:39.594Z",
            "updatedAt": "2020-05-28T13:38:23.312Z",
            "tags": [],
            "classTitle": "Corrosion",
            "points": {
                "exterior": [
                    [
                        559,
                        0
                    ],
                    [
                        555,
                        2
                    ],
                    [
                        552,
                        8
                    ],
                    [
                        547,
                        14
                    ],
                    [
                        539,
                        19
                    ],
                    [
                        526,
                        22
                    ],
                    [
                        517,
                        28
                    ],
                    [
                        510,
                        31
                    ],
                    [
                        495,
                        36
                    ],
                    [
                        486,
                        38
                    ],
                    [
                        472,
                        43
                    ],
                    [
                        461,
                        45
                    ],
                    [
                        440,
                        57
                    ],
                    [
                        434,
                        62
                    ],
                    [
                        428,
                        66
                    ],
                    [
                        416,
                        74
                    ],
                    [
                        418,
                        68
                    ],
                    [
                        423,
                        63
                    ],
                    [
                        427,
                        60
                    ],
                    [
                        431,
                        58
                    ],
                    [
                        434,
                        52
                    ],
                    [
                        438,
                        49
                    ],
                    [
                        446,
                        44
                    ],
                    [
                        450,
                        38
                    ],
                    [
                        453,
                        33
                    ],
                    [
                        461,
                        29
                    ],
                    [
                        467,
                        28
                    ],
                    [
                        471,
                        24
                    ],
                    [
                        478,
                        20
                    ],
                    [
                        482,
                        16
                    ],
                    [
                        484,
                        14
                    ],
                    [
                        482,
                        12
                    ],
                    [
                        477,
                        10
                    ],
                    [
                        483,
                        4
                    ],
                    [
                        488,
                        0
                    ]
                ],
                "interior": []
            }
        },
        {
            "id": 448828166,
            "classId": 1485631,
            "description": "",
            "geometryType": "polygon",
            "labelerLogin": "tug85997@temple.edu",
            "createdAt": "2020-05-21T15:20:26.181Z",
            "updatedAt": "2020-05-28T13:38:23.312Z",
            "tags": [],
            "classTitle": "Corrosion",
            "points": {
                "exterior": [
                    [
                        31,
                        182
                    ],
                    [
                        24,
                        192
                    ],
                    [
                        17,
                        202
                    ],
                    [
                        13,
                        213
                    ],
                    [
                        9,
                        223
                    ],
                    [
                        7,
                        232
                    ],
                    [
                        0,
                        247
                    ],
                    [
                        0,
                        309
                    ],
                    [
                        6,
                        304
                    ],
                    [
                        13,
                        296
                    ],
                    [
                        19,
                        294
                    ],
                    [
                        26,
                        294
                    ],
                    [
                        32,
                        294
                    ],
                    [
                        24,
                        286
                    ],
                    [
                        21,
                        283
                    ],
                    [
                        16,
                        279
                    ],
                    [
                        13,
                        276
                    ],
                    [
                        10,
                        274
                    ],
                    [
                        9,
                        268
                    ],
                    [
                        13,
                        253
                    ],
                    [
                        16,
                        249
                    ],
                    [
                        20,
                        244
                    ],
                    [
                        20,
                        231
                    ],
                    [
                        21,
                        225
                    ],
                    [
                        25,
                        205
                    ],
                    [
                        29,
                        198
                    ],
                    [
                        31,
                        192
                    ]
                ],
                "interior": []
            }
        },
        {
            "id": 448828185,
            "classId": 1485631,
            "description": "",
            "geometryType": "polygon",
            "labelerLogin": "tug85997@temple.edu",
            "createdAt": "2020-05-21T15:20:51.453Z",
            "updatedAt": "2020-05-28T13:38:23.312Z",
            "tags": [],
            "classTitle": "Corrosion",
            "points": {
                "exterior": [
                    [
                        36,
                        208
                    ],
                    [
                        42,
                        214
                    ],
                    [
                        49,
                        209
                    ],
                    [
                        51,
                        206
                    ],
                    [
                        45,
                        204
                    ],
                    [
                        47,
                        200
                    ],
                    [
                        50,
                        196
                    ],
                    [
                        51,
                        189
                    ],
                    [
                        44,
                        188
                    ],
                    [
                        40,
                        186
                    ],
                    [
                        39,
                        181
                    ],
                    [
                        36,
                        185
                    ],
                    [
                        34,
                        193
                    ],
                    [
                        32,
                        198
                    ],
                    [
                        32,
                        202
                    ]
                ],
                "interior": []
            }
        },
        {
            "id": 448828251,
            "classId": 1485631,
            "description": "",
            "geometryType": "polygon",
            "labelerLogin": "tug85997@temple.edu",
            "createdAt": "2020-05-21T15:21:07.479Z",
            "updatedAt": "2020-05-28T13:38:23.312Z",
            "tags": [],
            "classTitle": "Corrosion",
            "points": {
                "exterior": [
                    [
                        313,
                        205
                    ],
                    [
                        306,
                        200
                    ],
                    [
                        299,
                        200
                    ],
                    [
                        294,
                        206
                    ],
                    [
                        292,
                        209
                    ],
                    [
                        296,
                        212
                    ],
                    [
                        299,
                        217
                    ],
                    [
                        302,
                        219
                    ],
                    [
                        304,
                        214
                    ],
                    [
                        307,
                        209
                    ]
                ],
                "interior": []
            }
        },
        {
            "id": 448828279,
            "classId": 1485631,
            "description": "",
            "geometryType": "polygon",
            "labelerLogin": "tug85997@temple.edu",
            "createdAt": "2020-05-21T15:21:14.787Z",
            "updatedAt": "2020-05-28T13:38:23.312Z",
            "tags": [],
            "classTitle": "Corrosion",
            "points": {
                "exterior": [
                    [
                        355,
                        218
                    ],
                    [
                        345,
                        218
                    ],
                    [
                        338,
                        224
                    ],
                    [
                        330,
                        224
                    ],
                    [
                        321,
                        225
                    ],
                    [
                        319,
                        225
                    ],
                    [
                        314,
                        228
                    ],
                    [
                        310,
                        234
                    ],
                    [
                        314,
                        235
                    ],
                    [
                        318,
                        236
                    ],
                    [
                        322,
                        242
                    ],
                    [
                        326,
                        239
                    ],
                    [
                        327,
                        235
                    ],
                    [
                        335,
                        231
                    ],
                    [
                        339,
                        230
                    ],
                    [
                        343,
                        233
                    ],
                    [
                        345,
                        238
                    ],
                    [
                        348,
                        236
                    ],
                    [
                        348,
                        228
                    ],
                    [
                        352,
                        226
                    ],
                    [
                        357,
                        224
                    ]
                ],
                "interior": []
            }
        },
        {
            "id": 448828287,
            "classId": 1485631,
            "description": "",
            "geometryType": "polygon",
            "labelerLogin": "tug85997@temple.edu",
            "createdAt": "2020-05-21T15:21:34.214Z",
            "updatedAt": "2020-05-28T13:38:23.312Z",
            "tags": [],
            "classTitle": "Corrosion",
            "points": {
                "exterior": [
                    [
                        518,
                        148
                    ],
                    [
                        505,
                        147
                    ],
                    [
                        495,
                        152
                    ],
                    [
                        494,
                        160
                    ],
                    [
                        501,
                        162
                    ],
                    [
                        505,
                        166
                    ],
                    [
                        507,
                        173
                    ],
                    [
                        510,
                        172
                    ],
                    [
                        510,
                        165
                    ],
                    [
                        516,
                        164
                    ],
                    [
                        525,
                        162
                    ],
                    [
                        529,
                        159
                    ],
                    [
                        532,
                        164
                    ],
                    [
                        537,
                        164
                    ],
                    [
                        540,
                        158
                    ],
                    [
                        543,
                        152
                    ],
                    [
                        540,
                        148
                    ],
                    [
                        536,
                        144
                    ],
                    [
                        523,
                        147
                    ]
                ],
                "interior": []
            }
        },
        {
            "id": 448828295,
            "classId": 1485631,
            "description": "",
            "geometryType": "polygon",
            "labelerLogin": "tug85997@temple.edu",
            "createdAt": "2020-05-21T15:21:50.652Z",
            "updatedAt": "2020-05-28T13:38:23.312Z",
            "tags": [],
            "classTitle": "Corrosion",
            "points": {
                "exterior": [
                    [
                        519,
                        180
                    ],
                    [
                        514,
                        182
                    ],
                    [
                        509,
                        185
                    ],
                    [
                        507,
                        188
                    ],
                    [
                        509,
                        191
                    ],
                    [
                        514,
                        190
                    ],
                    [
                        517,
                        194
                    ],
                    [
                        519,
                        198
                    ],
                    [
                        522,
                        194
                    ],
                    [
                        525,
                        190
                    ],
                    [
                        531,
                        186
                    ],
                    [
                        535,
                        186
                    ],
                    [
                        538,
                        186
                    ],
                    [
                        540,
                        191
                    ],
                    [
                        542,
                        191
                    ],
                    [
                        545,
                        189
                    ],
                    [
                        545,
                        184
                    ],
                    [
                        547,
                        182
                    ],
                    [
                        548,
                        179
                    ],
                    [
                        543,
                        178
                    ],
                    [
                        536,
                        177
                    ],
                    [
                        530,
                        178
                    ],
                    [
                        526,
                        178
                    ]
                ],
                "interior": []
            }
        },
        {
            "id": 448828310,
            "classId": 1485631,
            "description": "",
            "geometryType": "polygon",
            "labelerLogin": "tug85997@temple.edu",
            "createdAt": "2020-05-21T15:22:23.069Z",
            "updatedAt": "2020-05-28T13:38:23.312Z",
            "tags": [],
            "classTitle": "Corrosion",
            "points": {
                "exterior": [
                    [
                        563,
                        340
                    ],
                    [
                        559,
                        340
                    ],
                    [
                        555,
                        342
                    ],
                    [
                        554,
                        346
                    ],
                    [
                        554,
                        352
                    ],
                    [
                        552,
                        351
                    ],
                    [
                        552,
                        349
                    ],
                    [
                        551,
                        347
                    ],
                    [
                        549,
                        346
                    ],
                    [
                        549,
                        342
                    ],
                    [
                        542,
                        342
                    ],
                    [
                        535,
                        344
                    ],
                    [
                        525,
                        349
                    ],
                    [
                        520,
                        353
                    ],
                    [
                        515,
                        357
                    ],
                    [
                        510,
                        360
                    ],
                    [
                        503,
                        366
                    ],
                    [
                        493,
                        373
                    ],
                    [
                        485,
                        380
                    ],
                    [
                        480,
                        384
                    ],
                    [
                        474,
                        388
                    ],
                    [
                        469,
                        391
                    ],
                    [
                        458,
                        400
                    ],
                    [
                        456,
                        400
                    ],
                    [
                        460,
                        395
                    ],
                    [
                        466,
                        390
                    ],
                    [
                        472,
                        386
                    ],
                    [
                        477,
                        382
                    ],
                    [
                        481,
                        379
                    ],
                    [
                        487,
                        375
                    ],
                    [
                        493,
                        370
                    ],
                    [
                        497,
                        367
                    ],
                    [
                        501,
                        364
                    ],
                    [
                        508,
                        359
                    ],
                    [
                        513,
                        355
                    ],
                    [
                        515,
                        352
                    ],
                    [
                        515,
                        350
                    ],
                    [
                        512,
                        349
                    ],
                    [
                        507,
                        350
                    ],
                    [
                        495,
                        353
                    ],
                    [
                        479,
                        357
                    ],
                    [
                        462,
                        361
                    ],
                    [
                        452,
                        363
                    ],
                    [
                        454,
                        366
                    ],
                    [
                        453,
                        370
                    ],
                    [
                        453,
                        373
                    ],
                    [
                        449,
                        374
                    ],
                    [
                        449,
                        371
                    ],
                    [
                        448,
                        369
                    ],
                    [
                        447,
                        365
                    ],
                    [
                        431,
                        368
                    ],
                    [
                        439,
                        361
                    ],
                    [
                        446,
                        361
                    ],
                    [
                        447,
                        357
                    ],
                    [
                        451,
                        354
                    ],
                    [
                        452,
                        358
                    ],
                    [
                        458,
                        357
                    ],
                    [
                        476,
                        353
                    ],
                    [
                        488,
                        350
                    ],
                    [
                        503,
                        346
                    ],
                    [
                        514,
                        343
                    ],
                    [
                        524,
                        341
                    ],
                    [
                        536,
                        339
                    ],
                    [
                        542,
                        338
                    ],
                    [
                        548,
                        336
                    ],
                    [
                        550,
                        335
                    ],
                    [
                        555,
                        335
                    ],
                    [
                        559,
                        336
                    ]
                ],
                "interior": []
            }
        },
        {
            "id": 448828406,
            "classId": 1485631,
            "description": "",
            "geometryType": "polygon",
            "labelerLogin": "tug85997@temple.edu",
            "createdAt": "2020-05-21T15:24:49.667Z",
            "updatedAt": "2020-05-28T13:38:23.312Z",
            "tags": [],
            "classTitle": "Corrosion",
            "points": {
                "exterior": [
                    [
                        344,
                        378
                    ],
                    [
                        349,
                        385
                    ],
                    [
                        357,
                        385
                    ],
                    [
                        363,
                        384
                    ],
                    [
                        365,
                        391
                    ],
                    [
                        367,
                        394
                    ],
                    [
                        368,
                        391
                    ],
                    [
                        368,
                        389
                    ],
                    [
                        368,
                        382
                    ],
                    [
                        374,
                        381
                    ],
                    [
                        385,
                        379
                    ],
                    [
                        390,
                        378
                    ],
                    [
                        396,
                        373
                    ],
                    [
                        390,
                        374
                    ],
                    [
                        379,
                        376
                    ],
                    [
                        368,
                        378
                    ],
                    [
                        362,
                        379
                    ],
                    [
                        355,
                        379
                    ],
                    [
                        352,
                        378
                    ],
                    [
                        352,
                        379
                    ],
                    [
                        353,
                        382
                    ],
                    [
                        351,
                        382
                    ],
                    [
                        350,
                        380
                    ],
                    [
                        347,
                        378
                    ]
                ],
                "interior": []
            }
        },
        {
            "id": 448828541,
            "classId": 1485631,
            "description": "",
            "geometryType": "polygon",
            "labelerLogin": "tug85997@temple.edu",
            "createdAt": "2020-05-21T15:25:14.736Z",
            "updatedAt": "2020-05-28T13:38:23.312Z",
            "tags": [],
            "classTitle": "Corrosion",
            "points": {
                "exterior": [
                    [
                        583,
                        314
                    ],
                    [
                        581,
                        312
                    ],
                    [
                        575,
                        314
                    ],
                    [
                        573,
                        315
                    ],
                    [
                        576,
                        318
                    ],
                    [
                        578,
                        321
                    ],
                    [
                        580,
                        319
                    ],
                    [
                        580,
                        317
                    ]
                ],
                "interior": []
            }
        },
        {
            "id": 448828545,
            "classId": 1485631,
            "description": "",
            "geometryType": "polygon",
            "labelerLogin": "tug85997@temple.edu",
            "createdAt": "2020-05-21T15:25:23.020Z",
            "updatedAt": "2020-05-28T13:38:23.312Z",
            "tags": [],
            "classTitle": "Corrosion",
            "points": {
                "exterior": [
                    [
                        564,
                        328
                    ],
                    [
                        561,
                        330
                    ],
                    [
                        562,
                        332
                    ],
                    [
                        565,
                        333
                    ],
                    [
                        566,
                        333
                    ],
                    [
                        567,
                        331
                    ],
                    [
                        568,
                        328
                    ]
                ],
                "interior": []
            }
        },
        {
            "id": 448828552,
            "classId": 1485631,
            "description": "",
            "geometryType": "polygon",
            "labelerLogin": "tug85997@temple.edu",
            "createdAt": "2020-05-21T15:25:29.509Z",
            "updatedAt": "2020-05-28T13:38:23.312Z",
            "tags": [],
            "classTitle": "Corrosion",
            "points": {
                "exterior": [
                    [
                        581,
                        326
                    ],
                    [
                        579,
                        327
                    ],
                    [
                        580,
                        328
                    ],
                    [
                        580,
                        330
                    ],
                    [
                        582,
                        331
                    ],
                    [
                        583,
                        329
                    ],
                    [
                        584,
                        327
                    ]
                ],
                "interior": []
            }
        },
        {
            "id": 451195629,
            "classId": 1485631,
            "description": "",
            "geometryType": "polygon",
            "labelerLogin": "bgarrisn",
            "createdAt": "2020-05-28T13:37:55.348Z",
            "updatedAt": "2020-05-28T13:38:23.312Z",
            "tags": [],
            "classTitle": "Corrosion",
            "points": {
                "exterior": [
                    [
                        405,
                        75
                    ],
                    [
                        405,
                        75
                    ],
                    [
                        329,
                        133
                    ],
                    [
                        303,
                        128
                    ],
                    [
                        231,
                        182
                    ],
                    [
                        171,
                        233
                    ],
                    [
                        121,
                        268
                    ],
                    [
                        140,
                        284
                    ],
                    [
                        212,
                        227
                    ],
                    [
                        278,
                        176
                    ],
                    [
                        315,
                        150
                    ]
                ],
                "interior": []
            }
        },
        {
            "id": 451195640,
            "classId": 1485631,
            "description": "",
            "geometryType": "polygon",
            "labelerLogin": "bgarrisn",
            "createdAt": "2020-05-28T13:38:09.977Z",
            "updatedAt": "2020-05-28T13:38:23.312Z",
            "tags": [],
            "classTitle": "Corrosion",
            "points": {
                "exterior": [
                    [
                        502,
                        301
                    ],
                    [
                        480,
                        315
                    ],
                    [
                        488,
                        323
                    ],
                    [
                        500,
                        312
                    ]
                ],
                "interior": []
            }
        },
        {
            "id": 451195643,
            "classId": 1485631,
            "description": "",
            "geometryType": "polygon",
            "labelerLogin": "bgarrisn",
            "createdAt": "2020-05-28T13:38:14.598Z",
            "updatedAt": "2020-05-28T13:38:23.312Z",
            "tags": [],
            "classTitle": "Corrosion",
            "points": {
                "exterior": [
                    [
                        462,
                        330
                    ],
                    [
                        448,
                        341
                    ],
                    [
                        453,
                        350
                    ],
                    [
                        469,
                        336
                    ]
                ],
                "interior": []
            }
        },
        {
            "id": 451195650,
            "classId": 1485631,
            "description": "",
            "geometryType": "polygon",
            "labelerLogin": "bgarrisn",
            "createdAt": "2020-05-28T13:38:22.797Z",
            "updatedAt": "2020-05-28T13:38:28.794Z",
            "tags": [],
            "classTitle": "Corrosion",
            "points": {
                "exterior": [
                    [
                        542,
                        347
                    ],
                    [
                        481,
                        389
                    ],
                    [
                        519,
                        365
                    ],
                    [
                        531,
                        353
                    ]
                ],
                "interior": []
            }
        }
    ]
}